{
  "category:modules": [
    {
      "id": "eclipse-allinone",
      "name": "ECLIPSE ALL IN ONE",
      "pkg": "com.eclipse.allinone.8spine",
      "file": "eclipseAllInOne.8spine",
      "download": "modules/eclipseAllInOne.8spine",
      "version": "v1.0.0",
      "code": 100,
      "type": "STREAM",
      "author": "Eclipse Community",
      "description": "HIFI LOSSLESS, SOUNDCLOUD, PODCASTS, RADIO & INTERNET ARCHIVE IN ONE",
      "tags": ["LOSSLESS", "MULTI-SOURCE", "FREE"],
      "featured": true,
      "trusted": true,
      "nsfw": false,
      "size": 3640,
      "lang": "all",
      "folder": "modules",
      "sources": [{ "name": "ECLIPSE ALL IN ONE", "lang": "all", "id": "eclipse-allinone", "baseUrl": "." }]
    },
    {
      "id": "eclipse-ytmusic",
      "name": "ECLIPSE YOUTUBE MUSIC",
      "pkg": "com.eclipse.ytmusic.8spine",
      "file": "eclipseYTMusic.8spine",
      "download": "modules/eclipseYTMusic.8spine",
      "version": "v1.0.0",
      "code": 100,
      "type": "STREAM",
      "author": "Eclipse Community",
      "description": "STREAM YOUTUBE MUSIC VIA ECLIPSE",
      "tags": ["YT MUSIC", "HIGH QUALITY", "FREE"],
      "featured": false,
      "trusted": true,
      "nsfw": false,
      "size": 3534,
      "lang": "all",
      "folder": "modules",
      "sources": [{ "name": "ECLIPSE YOUTUBE MUSIC", "lang": "all", "id": "eclipse-ytmusic", "baseUrl": "." }]
    },
    {
      "id": "eclipse-deezertidal",
      "name": "ECLIPSE DEEZER / TIDAL",
      "pkg": "com.eclipse.deezertidal.8spine",
      "file": "eclipseDeezerTidal.8spine",
      "download": "modules/eclipseDeezerTidal.8spine",
      "version": "v1.0.0",
      "code": 100,
      "type": "STREAM",
      "author": "Eclipse Community",
      "description": "LOSSLESS AUDIO VIA DEEZER AND TIDAL",
      "tags": ["LOSSLESS", "FLAC", "TIDAL"],
      "featured": false,
      "trusted": true,
      "nsfw": false,
      "size": 3637,
      "lang": "all",
      "folder": "modules",
      "sources": [{ "name": "ECLIPSE DEEZER / TIDAL", "lang": "all", "id": "eclipse-deezertidal", "baseUrl": "." }]
    },
    {
      "id": "eclipse-soundcloud",
      "name": "ECLIPSE SOUNDCLOUD",
      "pkg": "com.eclipse.soundcloud.8spine",
      "file": "eclipseSoundCloud.8spine",
      "download": "modules/eclipseSoundCloud.8spine",
      "version": "v1.0.0",
      "code": 100,
      "type": "STREAM",
      "author": "Eclipse Community",
      "description": "SEARCH AND STREAM TRACKS FROM SOUNDCLOUD",
      "tags": ["SOUNDCLOUD", "MP3", "FREE"],
      "featured": false,
      "trusted": true,
      "nsfw": false,
      "size": 2704,
      "lang": "all",
      "folder": "modules",
      "sources": [{ "name": "ECLIPSE SOUNDCLOUD", "lang": "all", "id": "eclipse-soundcloud", "baseUrl": "." }]
    },
    {
      "id": "eclipse-monochrome",
      "name": "ECLIPSE MONOCHROME",
      "pkg": "com.eclipse.monochrome.8spine",
      "file": "eclipseMonochrome.8spine",
      "download": "modules/eclipseMonochrome.8spine",
      "version": "v1.0.0",
      "code": 100,
      "type": "STREAM",
      "author": "Eclipse Community",
      "description": "TIDAL + QOBUZ HI-RES VIA MONOCHROME",
      "tags": ["LOSSLESS", "TIDAL", "QOBUZ"],
      "featured": false,
      "trusted": true,
      "nsfw": false,
      "size": 3625,
      "lang": "all",
      "folder": "modules",
      "sources": [{ "name": "ECLIPSE MONOCHROME", "lang": "all", "id": "eclipse-monochrome", "baseUrl": "." }]
    }
  ],
  "category:debrid_modules": [],
  "category:artworks": [],
  "category:testing": []
}
